orthant/__init__.py
orthant/cli.py
orthant/commands.py
orthant/configs.py
orthant/graph.py
orthant/schema.py
orthant/templates.py
orthant/utils.py
orthant-0.1.2.dist-info/METADATA
orthant-0.1.2.dist-info/WHEEL
orthant-0.1.2.dist-info/entry_points.txt
orthant-0.1.2.dist-info/licenses/LICENSE
orthant-0.1.2.dist-info/RECORD
